hissw/__init__.py
hissw/environment.py
hissw/read_config.py
hissw/util.py
hissw/templates/parent.pro
hissw/templates/procedure.pro
hissw/templates/startup.sh
hissw-1.2.dist-info/LICENSE
hissw-1.2.dist-info/METADATA
hissw-1.2.dist-info/WHEEL
hissw-1.2.dist-info/top_level.txt
hissw-1.2.dist-info/RECORD
