Metadata-Version: 2.1
Name: hissw
Version: 1.2
Summary: Seamlessly integrate SSWIDL code into your Python workflow
Home-page: https://github.com/wtbarnes/hissw
Author: Will Barnes
Author-email: will.t.barnes@gmail.com
License: MIT
Project-URL: Documentation, https://wtbarnes.github.io/hissw/
Project-URL: Source, https://github.com/wtbarnes/hissw/
Keywords: solar sun ssw solar-physics idl sswidl solarsoft
Platform: UNKNOWN
Classifier: Development Status :: 5 - Production/Stable
Classifier: Intended Audience :: Science/Research
Classifier: License :: OSI Approved :: MIT License
Classifier: Programming Language :: Python :: 3
Requires-Python: >=3
License-File: LICENSE
Requires-Dist: jinja2
Requires-Dist: scipy
